CrystalMatch/__init__.py
CrystalMatch/dls_focusstack/__init__.py
CrystalMatch/dls_focusstack/main_service.py
CrystalMatch/dls_focusstack/config/__init__.py
CrystalMatch/dls_focusstack/config/focus_config.py
CrystalMatch/dls_focusstack/focus/__init__.py
CrystalMatch/dls_focusstack/focus/focus_stack_lap_pyramid.py
CrystalMatch/dls_focusstack/focus/fourier.py
CrystalMatch/dls_focusstack/focus/image_fft_manager.py
CrystalMatch/dls_focusstack/focus/imagefft.py
CrystalMatch/dls_focusstack/focus/point_fft_manager.py
CrystalMatch/dls_focusstack/focus/pointfft.py
CrystalMatch/dls_focusstack/focus/pyramid.py
CrystalMatch/dls_focusstack/focus/pyramid_collection.py
CrystalMatch/dls_focusstack/focus/pyramid_level.py
CrystalMatch/dls_focusstack/focus/pyramid_manager.py
CrystalMatch/dls_focusstack/focus/sharpness_detector.py
CrystalMatch/dls_focusstack/focus/test_focus_stack_lap_pyramid.py
CrystalMatch/dls_focusstack/focus/test_image_fft.py
CrystalMatch/dls_focusstack/focus/test_image_fft_manager.py
CrystalMatch/dls_focusstack/focus/test_pointFFT.py
CrystalMatch/dls_focusstack/focus/test_pointFFTManager.py
CrystalMatch/dls_focusstack/focus/test_pyramid.py
CrystalMatch/dls_focusstack/focus/test_pyramid_collection.py
CrystalMatch/dls_focusstack/focus/test_pyramid_level.py
CrystalMatch/dls_focusstack/focus/test_pyramid_manager.py
CrystalMatch/dls_focusstack/focus/test_sharpness_detector.py
CrystalMatch/dls_imagematch/__init__.py
CrystalMatch/dls_imagematch/logconfig.py
CrystalMatch/dls_imagematch/main_service.py
CrystalMatch/dls_imagematch/version.py
CrystalMatch/dls_imagematch/crystal/__init__.py
CrystalMatch/dls_imagematch/crystal/align/__init__.py
CrystalMatch/dls_imagematch/crystal/align/aligned_images.py
CrystalMatch/dls_imagematch/crystal/align/aligner.py
CrystalMatch/dls_imagematch/crystal/align/config.py
CrystalMatch/dls_imagematch/crystal/align/exception.py
CrystalMatch/dls_imagematch/crystal/align/metric_overlap.py
CrystalMatch-1.2.2.dist-info/METADATA
CrystalMatch-1.2.2.dist-info/RECORD
CrystalMatch-1.2.2.dist-info/WHEEL
CrystalMatch-1.2.2.dist-info/entry_points.txt
CrystalMatch-1.2.2.dist-info/top_level.txt
