Metadata-Version: 2.1
Name: CrystalMatch
Version: 1.2.2
Summary: Python Toolkit for Matching Points on Formulatrix Images to Points on Beamline Images
Home-page: https://github.com/DiamondLightSource/CrystalMatch
Author: Urszula Neuman
Author-email: urszula.neuman@dimaond.ac.uk
License: Apache License 2.0
Platform: UNKNOWN
Classifier: Development Status :: 3 - Alpha
Classifier: Intended Audience :: Developers
Classifier: License :: OSI Approved :: Apache Software License
Classifier: Programming Language :: Python :: 2.7
Requires-Dist: numpy (>=1.11.1)
Requires-Dist: scipy (>=0.19.1)
Requires-Dist: pygelf (>=0.3.1)
